{
  "file_name": "src/store.ts",
  "revision_id": "9c39f262-43ed-4d53-975f-038af0a8f693",
  "metadata": {
    "timestamp": "2026-03-15T13:28:50.408099",
    "type": "cache_version",
    "source": "ToolTextFileEdit",
    "size": 18953,
    "is_reverted": false,
    "git_branch_name": "main",
    "agent_name": "Cody",
    "description": ""
  },
  "content": "import { create } from 'zustand';\nimport { getDCATemplate, getGridTemplate, getGuardTemplate } from './templates';\n\n// ─── Web Audio SFX ────────────────────────────────────────────────────────────\n\nconst audioCtx = new (window.AudioContext || (window as any).webkitAudioContext)();\n\nfunction playSound(type: 'BUY' | 'SELL' | 'FAILED') {\n  if (audioCtx.state === 'suspended') audioCtx.resume();\n\n  if (type === 'FAILED') {\n    const osc = audioCtx.createOscillator();\n    const gain = audioCtx.createGain();\n    osc.type = 'square';\n    osc.frequency.setValueAtTime(100, audioCtx.currentTime);\n    gain.gain.setValueAtTime(0.08, audioCtx.currentTime);\n    gain.gain.exponentialRampToValueAtTime(0.001, audioCtx.currentTime + 0.18);\n    osc.connect(gain);\n    gain.connect(audioCtx.destination);\n    osc.start();\n    osc.stop(audioCtx.currentTime + 0.18);\n    return;\n  }\n\n  const now = audioCtx.currentTime;\n  const tones = type === 'BUY'\n    ? [{ freq: 2637, delay: 0 }, { freq: 3136, delay: 0.07 }]\n    : [{ freq: 2093, delay: 0 }, { freq: 2637, delay: 0.07 }];\n\n  for (const { freq, delay } of tones) {\n    const osc = audioCtx.createOscillator();\n    const gain = audioCtx.createGain();\n    osc.type = 'triangle';\n    osc.frequency.setValueAtTime(freq, now + delay);\n    gain.gain.setValueAtTime(0, now + delay);\n    gain.gain.linearRampToValueAtTime(0.18, now + delay + 0.005);\n    gain.gain.exponentialRampToValueAtTime(0.001, now + delay + 0.22);\n    osc.connect(gain);\n    gain.connect(audioCtx.destination);\n    osc.start(now + delay);\n    osc.stop(now + delay + 0.25);\n  }\n}\n\nexport interface OHLCCandle {\n  open: number;\n  high: number;\n  low: number;\n  close: number;\n}\n\nexport interface StrategyNode {\n  id: string;\n  type: 'CONDITION' | 'ACTION';\n  x: number;\n  y: number;\n  exp?: number;    // XP earned from successful trades\n  level?: number;  // Derived from exp: every 3 exp = +1 level (min 1)\n  data: {\n    label: string;\n    targetPrice?: number;\n    operator?: 'lt' | 'gt' | 'drop' | 'rise';\n    dropPercent?: number;\n    risePercent?: number;\n    side?: 'BUY' | 'SELL';\n    amount?: number;\n  };\n}\n\nexport interface Connection {\n  fromId: string;\n  toId: string;\n}\n\nexport interface TradeLog {\n  id: string;\n  message: string;\n  time: string;\n  type: 'BUY' | 'SELL' | 'FAILED';\n}\n\nexport interface ChartTrade {\n  id: string;\n  type: 'BUY' | 'SELL';\n  price: number;\n  historyIndex: number;\n}\n\n// ─── Position tracking ────────────────────────────────────────────────────────\nexport interface ActivePosition {\n  buyPrice: number;\n  triggerPrice?: number;\n  operator?: 'lt' | 'gt' | 'drop' | 'rise';\n}\n\nconst HISTORY_CAP = 10000;\n\ninterface SimulationState {\n  balance: number;\n  totalDeposits: number;\n  assets: Record<string, number>;\n  asset: string;\n  isRunning: boolean;\n  currentPrice: number;\n  priceHistory: OHLCCandle[];\n  chartType: 'LINE' | 'CANDLE';\n  simulationSpeed: number;\n  timeframe: '1s' | '1m' | '5m' | '1h';\n  chartTrades: ChartTrade[];\n  nodes: StrategyNode[];\n  connections: Connection[];\n  logs: TradeLog[];\n  trailingHigh: number;\n  trailingLow: number;\n  averageBuyPrice: number;\n\n  activePositions: Record<string, ActivePosition>;\n  recoveryModes: Record<string, ActivePosition>;\n  totalAllTimeProfit: number;\n  activePulseNode: string | null;\n  firstTickPrice: number | null;\n\n  toggleSimulation: () => void;\n  closeAllPositions: () => void;\n  tick: () => void;\n  triggerPulse: (nodeId: string) => void;\n  setChartType: (type: 'LINE' | 'CANDLE') => void;\n  setSimulationSpeed: (speed: number) => void;\n  setTimeframe: (tf: '1s' | '1m' | '5m' | '1h') => void;\n  setAsset: (newAsset: string) => void;\n  addNode: (node: StrategyNode) => void;\n  updateNodePosition: (id: string, x: number, y: number) => void;\n  updateNodeData: (id: string, data: Partial<StrategyNode['data']>) => void;\n  connectNodes: (fromId: string, toId: string) => void;\n  removeConnection: (fromId: string, toId: string) => void;\n  removeNode: (id: string) => void;\n  deposit: (amount: number) => void;\n  loadTemplate: (type: 'DCA' | 'GRID' | 'GUARD') => void;\n\n  triggerShock: (type: 'MOON' | 'CRASH') => void;\n\n  isExportOpen: boolean;\n  openExport: () => void;\n  closeExport: () => void;\n}\n\nconst INITIAL_PRICE = 65000;\n\nconst ASSET_BASE_PRICES: Record<string, number> = {\n  'BTC/USD': 65000,\n  'ETH/USD': 3500,\n  'EUR/USD': 1.12,\n};\n\nexport const useSimulationStore = create<SimulationState>((set, get) => ({\n  balance: 10000,\n  totalDeposits: 10000,\n  assets: { 'BTC/USD': 0, 'ETH/USD': 0, 'EUR/USD': 0 },\n  asset: 'BTC/USD',\n  isRunning: false,\n  currentPrice: INITIAL_PRICE,\n  trailingHigh: INITIAL_PRICE,\n  trailingLow: INITIAL_PRICE,\n  averageBuyPrice: 0,\n  priceHistory: [{ open: INITIAL_PRICE, high: INITIAL_PRICE, low: INITIAL_PRICE, close: INITIAL_PRICE }],\n  chartType: 'LINE',\n  simulationSpeed: 20,\n  timeframe: '1s',\n  chartTrades: [],\n  nodes: [],\n  connections: [],\n  logs: [],\n  activePositions: {},\n  recoveryModes: {},\n  totalAllTimeProfit: 0,\n  activePulseNode: null,\n  firstTickPrice: null,\n  isExportOpen: false,\n\n  toggleSimulation: () =>\n    set((state) => ({ isRunning: !state.isRunning })),\n\n  // ── Visual pulse: lights up the wire for 800ms ────────────────────────────\n  triggerPulse: (nodeId) => {\n    set({ activePulseNode: nodeId });\n    setTimeout(() => set({ activePulseNode: null }), 800);\n  },\n\n  setChartType: (type) => set({ chartType: type }),\n\n  setSimulationSpeed: (speed) => set({ simulationSpeed: speed }),\n\n  setTimeframe: (tf) => set({ timeframe: tf }),\n\n  setAsset: (newAsset) =>\n    set(() => {\n      const newBasePrice = ASSET_BASE_PRICES[newAsset] ?? 100;\n      const seedCandle: OHLCCandle = {\n        open: newBasePrice,\n        high: newBasePrice,\n        low: newBasePrice,\n        close: newBasePrice,\n      };\n      return {\n        asset: newAsset,\n        currentPrice: newBasePrice,\n        priceHistory: [seedCandle],\n        logs: [],\n        chartTrades: [],\n        connections: [],\n        activePositions: {},\n        recoveryModes: {},\n      };\n    }),\n\n  tick: () =>\n    set((state) => {\n      const lastCandle = state.priceHistory[state.priceHistory.length - 1];\n      const open = lastCandle.close;\n\n      // Each tick is always a 1-second tick — timeframe only affects aggregation in the chart\n      // Dynamic decimal precision: EUR/USD needs 5 decimals, others 2\n      const decimals = state.asset === 'EUR/USD' ? 5 : 2;\n\n      let change: number;\n      if (state.asset === 'EUR/USD') {\n        change = (Math.random() - 0.5) * 0.001;\n      } else if (state.asset === 'ETH/USD') {\n        change = (Math.random() - 0.5) * 40;\n      } else {\n        change = (Math.random() - 0.5) * 300;\n      }\n      const close = Math.max(0.0001, open + change);\n\n      // Wicks proportional to per-tick volatility (not flat % of price)\n      const wickUp   = Math.abs(change) * Math.random() * 1.5;\n      const wickDown = Math.abs(change) * Math.random() * 1.5;\n      const high = Math.max(open, close) + wickUp;\n      const low  = Math.min(open, close) - wickDown;\n\n      const price = parseFloat(close.toFixed(decimals));\n\n      // ── Track trailing extremes ───────────────────────────────────────────\n      let currentTrailingHigh = Math.max(state.trailingHigh, price);\n      let currentTrailingLow  = Math.min(state.trailingLow,  price);\n\n      const rawNewLength = state.priceHistory.length + 1;\n      const willShift = rawNewLength > HISTORY_CAP;\n      const shiftAmount = willShift ? rawNewLength - HISTORY_CAP : 0;\n      const newCandleIndex = Math.min(rawNewLength, HISTORY_CAP) - 1;\n\n      let newBalance = state.balance;\n      const newAssets: Record<string, number> = { ...state.assets };\n      let newAverageBuyPrice = state.averageBuyPrice;\n      const newLogs: TradeLog[] = [];\n      const newChartTrades: ChartTrade[] = [];\n      let tickRealizedProfit = 0;\n\n      const newActive   = { ...state.activePositions };\n      const newRecovery = { ...state.recoveryModes };\n      // Track node XP gains this tick (nodeId → xp delta)\n      const nodeXpGains: Record<string, number> = {};\n\n      // ── Recovery check ────────────────────────────────────────────────────\n      for (const nodeId in newRecovery) {\n        const pos = newRecovery[nodeId];\n        const trigger = pos.triggerPrice ?? pos.buyPrice;\n        // lt/drop nodes recover when price rises back above trigger; gt/rise when it falls back below\n        const recovered = (pos.operator === 'lt' || pos.operator === 'drop')\n          ? price > trigger\n          : price < trigger;\n        if (recovered) delete newRecovery[nodeId];\n      }\n\n      // ── Connection loop ───────────────────────────────────────────────────\n      for (const conn of state.connections) {\n        const condNode = state.nodes.find((n) => n.id === conn.fromId && n.type === 'CONDITION');\n        const actNode  = state.nodes.find((n) => n.id === conn.toId   && n.type === 'ACTION');\n        if (!condNode || !actNode) continue;\n\n        const { operator, targetPrice, dropPercent, risePercent } = condNode.data;\n        const { side, amount } = actNode.data;\n        if (!operator || !side || !amount) continue;\n\n        // ── Condition evaluation ──────────────────────────────────────────\n        let condMet = false;\n        if (operator === 'lt' && targetPrice != null) {\n          condMet = price < targetPrice;\n        } else if (operator === 'gt' && targetPrice != null) {\n          condMet = price > targetPrice;\n        } else if (operator === 'drop' && dropPercent != null) {\n          condMet = price <= currentTrailingHigh * (1 - dropPercent / 100);\n        } else if (operator === 'rise' && risePercent != null) {\n          const baseRisePrice = newAverageBuyPrice > 0 ? newAverageBuyPrice : currentTrailingLow;\n          condMet = price >= baseRisePrice * (1 + risePercent / 100);\n        }\n\n        if (!condMet) continue;\n        if (newRecovery[conn.toId]) continue;\n\n        const timeStr = new Date().toLocaleTimeString('en-US', { hour12: false });\n        const tradeId = `${Date.now()}-${Math.random()}`;\n\n        if (side === 'BUY') {\n          if (newActive[conn.toId]) continue;\n\n          if (amount > newBalance) {\n            playSound('FAILED');\n            newLogs.push({ id: tradeId, message: `FAILED: Insufficient funds (need $${amount})`, time: timeStr, type: 'FAILED' });\n            newRecovery[conn.toId] = { buyPrice: price, triggerPrice: targetPrice, operator };\n            continue;\n          }\n\n          const prevUnits  = newAssets[state.asset] || 0;\n          const newUnits   = amount / price;\n          const totalUnits = parseFloat((prevUnits + newUnits).toFixed(8));\n\n          newBalance = parseFloat((newBalance - amount).toFixed(2));\n          newAssets[state.asset] = totalUnits;\n\n          // ── Update weighted average buy price ─────────────────────────\n          if (prevUnits <= 0 || newAverageBuyPrice <= 0) {\n            newAverageBuyPrice = price;\n          } else {\n            newAverageBuyPrice = parseFloat(\n              ((newAverageBuyPrice * prevUnits + price * newUnits) / totalUnits).toFixed(decimals)\n            );\n          }\n\n          newActive[conn.toId] = { buyPrice: price, triggerPrice: targetPrice, operator };\n\n          // Award XP to both condition and action nodes\n          nodeXpGains[conn.fromId] = (nodeXpGains[conn.fromId] ?? 0) + 1;\n          nodeXpGains[conn.toId]   = (nodeXpGains[conn.toId]   ?? 0) + 1;\n\n          playSound('BUY');\n          newLogs.push({ id: tradeId, message: `BUY $${amount} (${newUnits.toFixed(4)} ${state.asset}) @ $${price.toFixed(2)}`, time: timeStr, type: 'BUY' });\n          newChartTrades.push({ id: tradeId, type: side, price, historyIndex: newCandleIndex });\n          // Trigger wire pulse animation\n          setTimeout(() => get().triggerPulse(conn.toId), 0);\n\n          // Reset trailing extremes after buy\n          currentTrailingHigh = price;\n          currentTrailingLow  = price;\n\n        } else {\n          // ── SELL ──────────────────────────────────────────────────────\n          const currentAssetUnits = newAssets[state.asset] || 0;\n          const pct       = Math.min(100, Math.max(1, amount));\n          const sellUnits = currentAssetUnits * (pct / 100);\n\n          // Nothing to sell — just skip, don't permanently block the node\n          if (sellUnits <= 0.000001) continue;\n\n          // ── Profit Protection: skip if price is at or below avg buy price\n          if (newAverageBuyPrice > 0 && price <= newAverageBuyPrice) continue;\n\n          const revenue = parseFloat((sellUnits * price).toFixed(2));\n          newAssets[state.asset] = parseFloat((currentAssetUnits - sellUnits).toFixed(8));\n          newBalance = parseFloat((newBalance + revenue).toFixed(2));\n\n          // Accumulate realized profit for this sell\n          const costBasis = sellUnits * (newAverageBuyPrice > 0 ? newAverageBuyPrice : price);\n          tickRealizedProfit += parseFloat((revenue - costBasis).toFixed(2));\n\n          // Reset averageBuyPrice on full exit\n          if (pct === 100) newAverageBuyPrice = 0;\n\n          // Award XP to both condition and action nodes\n          nodeXpGains[conn.fromId] = (nodeXpGains[conn.fromId] ?? 0) + 1;\n          nodeXpGains[conn.toId]   = (nodeXpGains[conn.toId]   ?? 0) + 1;\n\n          playSound('SELL');\n          newLogs.push({ id: tradeId, message: `SELL ${pct}% (${sellUnits.toFixed(6)} ${state.asset}, $${revenue}) @ $${price.toFixed(2)}`, time: timeStr, type: 'SELL' });\n          newChartTrades.push({ id: tradeId, type: side, price, historyIndex: newCandleIndex });\n          // Trigger wire pulse animation\n          setTimeout(() => get().triggerPulse(conn.toId), 0);\n\n          // Block sell node until price recovers\n          newRecovery[conn.toId] = { buyPrice: price, triggerPrice: targetPrice, operator };\n\n          // Reset trailing extremes after sell\n          currentTrailingHigh = price;\n          currentTrailingLow  = price;\n\n          for (const activeId in newActive) {\n            const pos = newActive[activeId];\n            if (price > pos.buyPrice) {\n              delete newActive[activeId];\n            } else {\n              newRecovery[activeId] = pos;\n              delete newActive[activeId];\n            }\n          }\n        }\n      }\n\n      const allLogs = [...newLogs, ...state.logs].slice(0, 50);\n\n      const newCandle: OHLCCandle = {\n        open:  parseFloat(open.toFixed(decimals)),\n        high:  parseFloat(high.toFixed(decimals)),\n        low:   parseFloat(low.toFixed(decimals)),\n        close: price,\n      };\n\n      const updatedChartTrades = [\n        ...state.chartTrades\n          .map((t) => ({ ...t, historyIndex: t.historyIndex - shiftAmount }))\n          .filter((t) => t.historyIndex >= 0),\n        ...newChartTrades,\n      ];\n\n      // Apply XP gains and compute new levels (every 3 exp = +1 level above base 1)\n      const updatedNodes = Object.keys(nodeXpGains).length > 0\n        ? state.nodes.map((n) => {\n            const gain = nodeXpGains[n.id];\n            if (!gain) return n;\n            const newExp   = (n.exp ?? 0) + gain;\n            const newLevel = Math.floor(newExp / 3) + 1;\n            return { ...n, exp: newExp, level: newLevel };\n          })\n        : state.nodes;\n\n      return {\n        currentPrice:       price,\n        trailingHigh:       currentTrailingHigh,\n        trailingLow:        currentTrailingLow,\n        averageBuyPrice:    newAverageBuyPrice,\n        balance:            newBalance,\n        assets:             newAssets,\n        priceHistory:       [...state.priceHistory, newCandle].slice(-HISTORY_CAP),\n        logs:               allLogs,\n        chartTrades:        updatedChartTrades,\n        activePositions:    newActive,\n        recoveryModes:      newRecovery,\n        connections:        state.connections,\n        nodes:              updatedNodes,\n        totalAllTimeProfit: parseFloat((state.totalAllTimeProfit + tickRealizedProfit).toFixed(2)),\n        // Capture the very first price tick as the Ghost Mode benchmark\n        firstTickPrice:     state.firstTickPrice ?? price,\n      };\n    }),\n\n  // ── God Mode ──────────────────────────────────────────────────────────────\n  triggerShock: (type) => set((state) => {\n    const decimals   = state.asset === 'EUR/USD' ? 5 : 2;\n    const multiplier = type === 'MOON' ? 1.15 : 0.80;\n    const newPrice   = parseFloat((state.currentPrice * multiplier).toFixed(decimals));\n    const shockCandle: OHLCCandle = {\n      open:  state.currentPrice,\n      high:  type === 'MOON' ? newPrice : state.currentPrice,\n      low:   type === 'CRASH' ? newPrice : state.currentPrice,\n      close: newPrice,\n    };\n    return {\n      currentPrice: newPrice,\n      trailingHigh: Math.max(state.trailingHigh, newPrice),\n      trailingLow:  Math.min(state.trailingLow,  newPrice),\n      priceHistory: [...state.priceHistory, shockCandle].slice(-HISTORY_CAP),\n    };\n  }),\n\n  // ── Export Modal ──────────────────────────────────────────────────────────\n  openExport:  () => set({ isExportOpen: true }),\n  closeExport: () => set({ isExportOpen: false }),\n\n  loadTemplate: (type) => set((state) => {\n    const template =\n      type === 'DCA'   ? getDCATemplate()   :\n      type === 'GRID'  ? getGridTemplate()  :\n      type === 'GUARD' ? getGuardTemplate() : null;\n    if (!template) return {};\n    // Offset each new node so it doesn't stack on top of existing ones\n    const offset = state.nodes.length * 15;\n    const adjustedNodes = template.nodes.map((n) => ({\n      ...n,\n      x: n.x + offset,\n      y: n.y + offset,\n    }));\n    return {\n      nodes:       [...state.nodes, ...adjustedNodes],\n      connections: [...state.connections, ...template.connections],\n    };\n  }),\n\n  addNode: (node) =>\n    set((state) => ({ nodes: [...state.nodes, node] })),\n\n  updateNodePosition: (id, x, y) =>\n    set((state) => ({\n      nodes: state.nodes.map((n) => (n.id === id ? { ...n, x, y } : n)),\n    })),\n\n  updateNodeData: (id, data) =>\n    set((state) => ({\n      nodes: state.nodes.map((n) =>\n        n.id === id ? { ...n, data: { ...n.data, ...data } } : n\n      ),\n    })),\n\n  connectNodes: (fromId, toId) =>\n    set((state) => {\n      const exists = state.connections.some(\n        (c) => c.fromId === fromId && c.toId === toId\n      );\n      if (exists) return {};\n      return { connections: [...state.connections, { fromId, toId }] };\n    }),\n\n  removeConnection: (fromId, toId) =>\n    set((state) => ({\n      connections: state.connections.filter(\n        (c) => !(c.fromId === fromId && c.toId === toId)\n      ),\n    })),\n\n  removeNode: (id) =>\n    set((state) => ({\n      nodes: state.nodes.filter((n) => n.id !== id),\n      connections: state.connections.filter(\n        (c) => c.fromId !== id && c.toId !== id\n      ),\n    })),\n\n  deposit: (amount) =>\n    set((state) => ({\n      balance: parseFloat((state.balance + amount).toFixed(2)),\n      totalDeposits: state.totalDeposits + amount,\n    })),\n}));\n",
  "saved_at": "2026-03-15T13:28:50.408099"
}